webcli2/__init__.py
webcli2/apilog.py
webcli2/config.py
webcli2/service_loader.py
webcli2/action_handlers/README.md
webcli2/action_handlers/__init__.py
webcli2/action_handlers/action_handler.py
webcli2/action_handlers/openai/README.md
webcli2/action_handlers/openai/__init__.py
webcli2/action_handlers/openai/main.py
webcli2/action_handlers/pyspark/README.md
webcli2/action_handlers/pyspark/__init__.py
webcli2/action_handlers/pyspark/main.py
webcli2/action_handlers/system/__init__.py
webcli2/action_handlers/system/main.py
webcli2/cli/__init__.py
webcli2/cli/main.py
webcli2/cli/main_internal.py
webcli2/core/__init__.py
webcli2/core/ai/__init__.py
webcli2/core/ai/ai_agent.py
webcli2/core/data/__init__.py
webcli2/core/data/data_accessor.py
webcli2/core/data/db_models/__init__.py
webcli2/core/data/db_models/_common.py
webcli2/core/data/db_models/db_action.py
webcli2/core/data/db_models/db_action_handler_configuration.py
webcli2/core/data/db_models/db_action_response_chunk.py
webcli2/core/data/db_models/db_thread.py
webcli2/core/data/db_models/db_thread_action.py
webcli2/core/data/db_models/db_user.py
webcli2/core/data/models/__init__.py
webcli2/core/data/models/action.py
webcli2/core/data/models/action_handler_configuration.py
webcli2/core/data/models/action_response_chunk.py
webcli2/core/data/models/thread.py
webcli2/core/data/models/thread_action.py
webcli2/core/data/models/user.py
webcli2/core/service/__init__.py
webcli2/core/service/notifications.py
webcli2/core/service/webcli_service.py
webcli2/web/__init__.py
webcli2/web/main.py
webcli2/web/dist/login_page.js
webcli2/web/dist/node_modules_mermaid-js_parser_dist_chunks_mermaid-parser_core_architecture-I3QFYML2_mjs.js
webcli2/web/dist/node_modules_mermaid-js_parser_dist_chunks_mermaid-parser_core_gitGraph-YCYPL57B_mjs.js
webcli2/web/dist/node_modules_mermaid-js_parser_dist_chunks_mermaid-parser_core_info-46DW6VJ7_mjs.js
webcli2-0.0.29.dist-info/METADATA
webcli2-0.0.29.dist-info/WHEEL
webcli2-0.0.29.dist-info/entry_points.txt
webcli2-0.0.29.dist-info/licenses/LICENSE
webcli2-0.0.29.dist-info/RECORD
